cbee/__init__.py
cbee/build.py
cbee/cli.py
cbee-0.1.2.dist-info/LICENSE
cbee-0.1.2.dist-info/METADATA
cbee-0.1.2.dist-info/WHEEL
cbee-0.1.2.dist-info/entry_points.txt
cbee-0.1.2.dist-info/top_level.txt
cbee-0.1.2.dist-info/RECORD
