Metadata-Version: 2.1
Name: cbee
Version: 0.1.2
Summary: C/C++ build tools and package manager.
Home-page: https://github.com/bee-field/cbee
Author: David Cavazos
Author-email: dcavazosw@gmail.com
License: UNKNOWN
Platform: UNKNOWN
Classifier: Development Status :: 3 - Alpha
Classifier: Environment :: Console
Classifier: Intended Audience :: Developers
Classifier: License :: OSI Approved :: MIT License
Classifier: Operating System :: OS Independent
Classifier: Programming Language :: Python :: 3
Classifier: Programming Language :: C
Classifier: Programming Language :: C++
Classifier: Topic :: Software Development :: Build Tools
Classifier: Topic :: Software Development :: Code Generators
Classifier: Topic :: Software Development :: Compilers
Requires-Dist: cmake
Requires-Dist: conan
